{"cameraMode":{"drawMode":0,"name":"Shaded","section":"Shading Mode"},"sceneLighting":true,"audioPlay":false,"sceneViewState":{"m_AlwaysRefresh":false,"showFog":true,"showSkybox":true,"showFlares":true,"showImageEffects":true,"showParticleSystems":true,"showVisualEffectGraphs":true,"m_FxEnabled":true},"in2DMode":false,"pivot":{"x":-0.5411550998687744,"y":0.7570594549179077,"z":11.53193187713623},"rotation":{"x":0.03654510900378227,"y":-0.18421724438667298,"z":-0.006854370702058077,"w":-0.9821944236755371},"size":1.926474928855896,"orthographic":false}